mewbot/io/discord/__init__.py
mewbot/io/discord/events.py
mewbot/io/discord/py.typed
mewbot_io_discord-0.0.4.dist-info/LICENSE.md
mewbot_io_discord-0.0.4.dist-info/METADATA
mewbot_io_discord-0.0.4.dist-info/WHEEL
mewbot_io_discord-0.0.4.dist-info/top_level.txt
mewbot_io_discord-0.0.4.dist-info/RECORD
