Metadata-Version: 2.1
Name: mewbot-io-discord
Version: 0.0.4
Summary: Mewbot bindings for discord.
Home-page: https://github.com/mewbotorg/mewbot-discord
Author: Alex Cameron
Author-email: mewbot@quicksilver.london
Maintainer: Alex Cameron
Maintainer-email: mewbot@quicksilver.london
License: Copyright (c) <year> <owner> All rights reserved.
Project-URL: Bug Tracker, https://github.com/mewbotorg/mewbot-discord/issues
Classifier: Development Status :: 4 - Beta
Classifier: Intended Audience :: Developers
Classifier: Programming Language :: Python
Classifier: Programming Language :: Python :: 3.10
Classifier: Programming Language :: Python :: 3.11
Classifier: Programming Language :: Python :: 3.12
Classifier: Programming Language :: Python :: 3 :: Only
Classifier: Programming Language :: Python :: Implementation :: CPython
Classifier: Programming Language :: Python :: Implementation :: PyPy
Classifier: Operating System :: OS Independent
Requires-Python: >=3.10
License-File: LICENSE.md
Requires-Dist: py-cord ~=2.4.1
Requires-Dist: mewbot ~=0.0.3
Requires-Dist: mewbot-api ~=0.0.3
Requires-Dist: mewbot-io ~=0.0.3
Requires-Dist: mewbot-test ~=0.0.3
